uetl.py
uetl-0.1.5.dist-info/LICENSE
uetl-0.1.5.dist-info/METADATA
uetl-0.1.5.dist-info/WHEEL
uetl-0.1.5.dist-info/top_level.txt
uetl-0.1.5.dist-info/RECORD
