Metadata-Version: 2.1
Name: uetl
Version: 0.1.5
Summary: Minimalist python ETL library.
Home-page: https://github.com/andrespp/uetl
Author: Andre Pereira
Author-email: andrespp@gmail.com
License: UNKNOWN
Platform: UNKNOWN
Classifier: Programming Language :: Python :: 3
Classifier: License :: OSI Approved :: MIT License
Classifier: Operating System :: OS Independent
License-File: LICENSE
Requires-Dist: SQLAlchemy (>=1.3)
Requires-Dist: fdb (>=2.0.2)
Requires-Dist: pandas (>=0.2)
Requires-Dist: psycopg2-binary (>=2.8)
Requires-Dist: pyodbc (>=4.0)
Provides-Extra: dev
Requires-Dist: check-manifest ; extra == 'dev'
Requires-Dist: pytest (>=3.7) ; extra == 'dev'
Requires-Dist: tox ; extra == 'dev'
Requires-Dist: twine ; extra == 'dev'
